{
  "systeminfo": "AVX = 0 | AVX2 = 0 | AVX512 = 0 | FMA = 0 | NEON = 1 | ARM_FMA = 1 | METAL = 1 | F16C = 0 | FP16_VA = 1 | WASM_SIMD = 0 | BLAS = 1 | SSE3 = 0 | SSSE3 = 0 | VSX = 0 | CUDA = 0 | COREML = 0 | OPENVINO = 0",
  "model": {
    "type": "medium",
    "multilingual": false,
    "vocab": 51864,
    "audio": {
      "ctx": 1500,
      "state": 1024,
      "head": 16,
      "layer": 24
    },
    "text": {
      "ctx": 448,
      "state": 1024,
      "head": 16,
      "layer": 24
    },
    "mels": 80,
    "ftype": 1
  },
  "params": {
    "model": "/Users/jonathanburger/our-recorder/whisper.cpp/ggml-medium.en.bin",
    "language": "en",
    "translate": false
  },
  "result": {
    "language": "en"
  },
  "transcription": [
    {
      "timestamps": {
        "from": "00:00:00,000",
        "to": "00:00:00,000"
      },
      "offsets": {
        "from": 0,
        "to": 0
      },
      "text": "",
      "tokens": [
        {
          "text": "[_BEG_]",
          "timestamps": {
            "from": "00:00:00,000",
            "to": "00:00:00,000"
          },
          "offsets": {
            "from": 0,
            "to": 0
          },
          "id": 50363,
          "p": 0.929062,
          "t_dtw": -1
        }
      ]
    },
    {
      "timestamps": {
        "from": "00:00:00,000",
        "to": "00:00:01,140"
      },
      "offsets": {
        "from": 0,
        "to": 1140
      },
      "text": " This",
      "tokens": [
        {
          "text": " This",
          "timestamps": {
            "from": "00:00:00,000",
            "to": "00:00:01,140"
          },
          "offsets": {
            "from": 0,
            "to": 1140
          },
          "id": 770,
          "p": 0.568428,
          "t_dtw": 498
        }
      ]
    },
    {
      "timestamps": {
        "from": "00:00:01,140",
        "to": "00:00:04,810"
      },
      "offsets": {
        "from": 1140,
        "to": 4810
      },
      "text": " new",
      "tokens": [
        {
          "text": " new",
          "timestamps": {
            "from": "00:00:01,140",
            "to": "00:00:01,700"
          },
          "offsets": {
            "from": 1140,
            "to": 1700
          },
          "id": 649,
          "p": 0.990116,
          "t_dtw": 518
        }
      ]
    },
    {
      "timestamps": {
        "from": "00:00:04,810",
        "to": "00:00:05,410"
      },
      "offsets": {
        "from": 4810,
        "to": 5410
      },
      "text": " architecture",
      "tokens": [
        {
          "text": " architecture",
          "timestamps": {
            "from": "00:00:04,810",
            "to": "00:00:05,410"
          },
          "offsets": {
            "from": 4810,
            "to": 5410
          },
          "id": 10959,
          "p": 0.987976,
          "t_dtw": 590
        }
      ]
    },
    {
      "timestamps": {
        "from": "00:00:05,410",
        "to": "00:00:06,000"
      },
      "offsets": {
        "from": 5410,
        "to": 6000
      },
      "text": ",",
      "tokens": [
        {
          "text": ",",
          "timestamps": {
            "from": "00:00:05,410",
            "to": "00:00:06,000"
          },
          "offsets": {
            "from": 5410,
            "to": 6000
          },
          "id": 11,
          "p": 0.600217,
          "t_dtw": 590
        }
      ]
    },
    {
      "timestamps": {
        "from": "00:00:06,000",
        "to": "00:00:06,210"
      },
      "offsets": {
        "from": 6000,
        "to": 6210
      },
      "text": " of",
      "tokens": [
        {
          "text": " of",
          "timestamps": {
            "from": "00:00:06,000",
            "to": "00:00:06,040"
          },
          "offsets": {
            "from": 6000,
            "to": 6040
          },
          "id": 286,
          "p": 0.978995,
          "t_dtw": 616
        }
      ]
    },
    {
      "timestamps": {
        "from": "00:00:06,210",
        "to": "00:00:06,630"
      },
      "offsets": {
        "from": 6210,
        "to": 6630
      },
      "text": " course",
      "tokens": [
        {
          "text": " course",
          "timestamps": {
            "from": "00:00:06,210",
            "to": "00:00:06,500"
          },
          "offsets": {
            "from": 6210,
            "to": 6500
          },
          "id": 1781,
          "p": 0.990038,
          "t_dtw": 656
        }
      ]
    },
    {
      "timestamps": {
        "from": "00:00:06,630",
        "to": "00:00:06,910"
      },
      "offsets": {
        "from": 6630,
        "to": 6910
      },
      "text": ",",
      "tokens": [
        {
          "text": ",",
          "timestamps": {
            "from": "00:00:06,630",
            "to": "00:00:06,760"
          },
          "offsets": {
            "from": 6630,
            "to": 6760
          },
          "id": 11,
          "p": 0.974223,
          "t_dtw": 694
        }
      ]
    },
    {
      "timestamps": {
        "from": "00:00:06,910",
        "to": "00:00:07,230"
      },
      "offsets": {
        "from": 6910,
        "to": 7230
      },
      "text": " makes",
      "tokens": [
        {
          "text": " makes",
          "timestamps": {
            "from": "00:00:06,910",
            "to": "00:00:07,140"
          },
          "offsets": {
            "from": 6910,
            "to": 7140
          },
          "id": 1838,
          "p": 0.845937,
          "t_dtw": 718
        }
      ]
    },
    {
      "timestamps": {
        "from": "00:00:07,230",
        "to": "00:00:07,440"
      },
      "offsets": {
        "from": 7230,
        "to": 7440
      },
      "text": " the",
      "tokens": [
        {
          "text": " the",
          "timestamps": {
            "from": "00:00:07,230",
            "to": "00:00:07,440"
          },
          "offsets": {
            "from": 7230,
            "to": 7440
          },
          "id": 262,
          "p": 0.973688,
          "t_dtw": 746
        }
      ]
    },
    {
      "timestamps": {
        "from": "00:00:07,440",
        "to": "00:00:07,630"
      },
      "offsets": {
        "from": 7440,
        "to": 7630
      },
      "text": " off",
      "tokens": [
        {
          "text": " off",
          "timestamps": {
            "from": "00:00:07,440",
            "to": "00:00:07,630"
          },
          "offsets": {
            "from": 7440,
            "to": 7630
          },
          "id": 572,
          "p": 0.852688,
          "t_dtw": 784
        }
      ]
    },
    {
      "timestamps": {
        "from": "00:00:07,630",
        "to": "00:00:07,830"
      },
      "offsets": {
        "from": 7630,
        "to": 7830
      },
      "text": "-",
      "tokens": [
        {
          "text": "-",
          "timestamps": {
            "from": "00:00:07,630",
            "to": "00:00:07,660"
          },
          "offsets": {
            "from": 7630,
            "to": 7660
          },
          "id": 12,
          "p": 0.923617,
          "t_dtw": 788
        }
      ]
    },
    {
      "timestamps": {
        "from": "00:00:07,830",
        "to": "00:00:08,120"
      },
      "offsets": {
        "from": 7830,
        "to": 8120
      },
      "text": "thread",
      "tokens": [
        {
          "text": "thread",
          "timestamps": {
            "from": "00:00:07,830",
            "to": "00:00:08,040"
          },
          "offsets": {
            "from": 7830,
            "to": 8040
          },
          "id": 16663,
          "p": 0.757428,
          "t_dtw": 800
        }
      ]
    },
    {
      "timestamps": {
        "from": "00:00:08,120",
        "to": "00:00:08,400"
      },
      "offsets": {
        "from": 8120,
        "to": 8400
      },
      "text": " video",
      "tokens": [
        {
          "text": " video",
          "timestamps": {
            "from": "00:00:08,120",
            "to": "00:00:08,400"
          },
          "offsets": {
            "from": 8120,
            "to": 8400
          },
          "id": 2008,
          "p": 0.90027,
          "t_dtw": 846
        }
      ]
    },
    {
      "timestamps": {
        "from": "00:00:08,400",
        "to": "00:00:09,510"
      },
      "offsets": {
        "from": 8400,
        "to": 9510
      },
      "text": " component",
      "tokens": [
        {
          "text": " component",
          "timestamps": {
            "from": "00:00:08,400",
            "to": "00:00:09,130"
          },
          "offsets": {
            "from": 8400,
            "to": 9130
          },
          "id": 7515,
          "p": 0.81984,
          "t_dtw": 912
        }
      ]
    },
    {
      "timestamps": {
        "from": "00:00:09,510",
        "to": "00:00:09,760"
      },
      "offsets": {
        "from": 9510,
        "to": 9760
      },
      "text": " much",
      "tokens": [
        {
          "text": " much",
          "timestamps": {
            "from": "00:00:09,510",
            "to": "00:00:09,750"
          },
          "offsets": {
            "from": 9510,
            "to": 9750
          },
          "id": 881,
          "p": 0.807511,
          "t_dtw": 980
        }
      ]
    },
    {
      "timestamps": {
        "from": "00:00:09,760",
        "to": "00:00:10,940"
      },
      "offsets": {
        "from": 9760,
        "to": 10940
      },
      "text": " faster",
      "tokens": [
        {
          "text": " faster",
          "timestamps": {
            "from": "00:00:09,760",
            "to": "00:00:10,450"
          },
          "offsets": {
            "from": 9760,
            "to": 10450
          },
          "id": 5443,
          "p": 0.951116,
          "t_dtw": 1034
        }
      ]
    },
    {
      "timestamps": {
        "from": "00:00:10,940",
        "to": "00:00:11,360"
      },
      "offsets": {
        "from": 10940,
        "to": 11360
      },
      "text": " since",
      "tokens": [
        {
          "text": " since",
          "timestamps": {
            "from": "00:00:10,940",
            "to": "00:00:11,360"
          },
          "offsets": {
            "from": 10940,
            "to": 11360
          },
          "id": 1201,
          "p": 0.357176,
          "t_dtw": 1130
        },
        {
          "text": "[_TT_568]",
          "timestamps": {
            "from": "00:00:11,360",
            "to": "00:00:11,360"
          },
          "offsets": {
            "from": 11360,
            "to": 11360
          },
          "id": 50931,
          "p": 0.108653,
          "t_dtw": -1
        }
      ]
    },
    {
      "timestamps": {
        "from": "00:00:11,360",
        "to": "00:00:11,930"
      },
      "offsets": {
        "from": 11360,
        "to": 11930
      },
      "text": " Rust",
      "tokens": [
        {
          "text": " Rust",
          "timestamps": {
            "from": "00:00:11,360",
            "to": "00:00:11,930"
          },
          "offsets": {
            "from": 11360,
            "to": 11930
          },
          "id": 17103,
          "p": 0.812583,
          "t_dtw": 1174
        }
      ]
    },
    {
      "timestamps": {
        "from": "00:00:11,930",
        "to": "00:00:12,350"
      },
      "offsets": {
        "from": 11930,
        "to": 12350
      },
      "text": " can",
      "tokens": [
        {
          "text": " can",
          "timestamps": {
            "from": "00:00:11,930",
            "to": "00:00:12,350"
          },
          "offsets": {
            "from": 11930,
            "to": 12350
          },
          "id": 460,
          "p": 0.995854,
          "t_dtw": 1204
        }
      ]
    },
    {
      "timestamps": {
        "from": "00:00:12,350",
        "to": "00:00:12,770"
      },
      "offsets": {
        "from": 12350,
        "to": 12770
      },
      "text": " use",
      "tokens": [
        {
          "text": " use",
          "timestamps": {
            "from": "00:00:12,350",
            "to": "00:00:12,770"
          },
          "offsets": {
            "from": 12350,
            "to": 12770
          },
          "id": 779,
          "p": 0.997185,
          "t_dtw": 1228
        }
      ]
    },
    {
      "timestamps": {
        "from": "00:00:12,770",
        "to": "00:00:13,240"
      },
      "offsets": {
        "from": 12770,
        "to": 13240
      },
      "text": " the",
      "tokens": [
        {
          "text": " the",
          "timestamps": {
            "from": "00:00:12,770",
            "to": "00:00:13,140"
          },
          "offsets": {
            "from": 12770,
            "to": 13140
          },
          "id": 262,
          "p": 0.972962,
          "t_dtw": 1246
        }
      ]
    },
    {
      "timestamps": {
        "from": "00:00:13,240",
        "to": "00:00:13,470"
      },
      "offsets": {
        "from": 13240,
        "to": 13470
      },
      "text": " FF",
      "tokens": [
        {
          "text": " FF",
          "timestamps": {
            "from": "00:00:13,240",
            "to": "00:00:13,440"
          },
          "offsets": {
            "from": 13240,
            "to": 13440
          },
          "id": 18402,
          "p": 0.41326,
          "t_dtw": 1290
        }
      ]
    },
    {
      "timestamps": {
        "from": "00:00:13,470",
        "to": "00:00:14,060"
      },
      "offsets": {
        "from": 13470,
        "to": 14060
      },
      "text": "mpeg",
      "tokens": [
        {
          "text": "mpeg",
          "timestamps": {
            "from": "00:00:13,470",
            "to": "00:00:13,960"
          },
          "offsets": {
            "from": 13470,
            "to": 13960
          },
          "id": 43913,
          "p": 0.780747,
          "t_dtw": 1338
        }
      ]
    },
    {
      "timestamps": {
        "from": "00:00:14,060",
        "to": "00:00:14,180"
      },
      "offsets": {
        "from": 14060,
        "to": 14180
      },
      "text": " C",
      "tokens": [
        {
          "text": " C",
          "timestamps": {
            "from": "00:00:14,060",
            "to": "00:00:14,180"
          },
          "offsets": {
            "from": 14060,
            "to": 14180
          },
          "id": 327,
          "p": 0.892091,
          "t_dtw": 1380
        }
      ]
    },
    {
      "timestamps": {
        "from": "00:00:14,180",
        "to": "00:00:15,000"
      },
      "offsets": {
        "from": 14180,
        "to": 15000
      },
      "text": " API",
      "tokens": [
        {
          "text": " API",
          "timestamps": {
            "from": "00:00:14,180",
            "to": "00:00:14,380"
          },
          "offsets": {
            "from": 14180,
            "to": 14380
          },
          "id": 7824,
          "p": 0.973395,
          "t_dtw": 1422
        }
      ]
    },
    {
      "timestamps": {
        "from": "00:00:15,000",
        "to": "00:00:15,080"
      },
      "offsets": {
        "from": 15000,
        "to": 15080
      },
      "text": ".",
      "tokens": [
        {
          "text": ".",
          "timestamps": {
            "from": "00:00:15,000",
            "to": "00:00:15,080"
          },
          "offsets": {
            "from": 15000,
            "to": 15080
          },
          "id": 13,
          "p": 0.97972,
          "t_dtw": 1486
        },
        {
          "text": "[_TT_754]",
          "timestamps": {
            "from": "00:00:15,080",
            "to": "00:00:15,080"
          },
          "offsets": {
            "from": 15080,
            "to": 15080
          },
          "id": 51117,
          "p": 0.162849,
          "t_dtw": -1
        }
      ]
    },
    {
      "timestamps": {
        "from": "00:00:15,080",
        "to": "00:00:15,360"
      },
      "offsets": {
        "from": 15080,
        "to": 15360
      },
      "text": " This",
      "tokens": [
        {
          "text": " This",
          "timestamps": {
            "from": "00:00:15,080",
            "to": "00:00:15,220"
          },
          "offsets": {
            "from": 15080,
            "to": 15220
          },
          "id": 770,
          "p": 0.998228,
          "t_dtw": 1512
        }
      ]
    },
    {
      "timestamps": {
        "from": "00:00:15,360",
        "to": "00:00:15,480"
      },
      "offsets": {
        "from": 15360,
        "to": 15480
      },
      "text": " is",
      "tokens": [
        {
          "text": " is",
          "timestamps": {
            "from": "00:00:15,360",
            "to": "00:00:15,480"
          },
          "offsets": {
            "from": 15360,
            "to": 15480
          },
          "id": 318,
          "p": 0.998517,
          "t_dtw": 1524
        }
      ]
    },
    {
      "timestamps": {
        "from": "00:00:15,480",
        "to": "00:00:15,820"
      },
      "offsets": {
        "from": 15480,
        "to": 15820
      },
      "text": " hard",
      "tokens": [
        {
          "text": " hard",
          "timestamps": {
            "from": "00:00:15,480",
            "to": "00:00:15,690"
          },
          "offsets": {
            "from": 15480,
            "to": 15690
          },
          "id": 1327,
          "p": 0.998403,
          "t_dtw": 1554
        }
      ]
    },
    {
      "timestamps": {
        "from": "00:00:15,820",
        "to": "00:00:15,880"
      },
      "offsets": {
        "from": 15820,
        "to": 15880
      },
      "text": " to",
      "tokens": [
        {
          "text": " to",
          "timestamps": {
            "from": "00:00:15,820",
            "to": "00:00:15,880"
          },
          "offsets": {
            "from": 15820,
            "to": 15880
          },
          "id": 284,
          "p": 0.999432,
          "t_dtw": 1572
        }
      ]
    },
    {
      "timestamps": {
        "from": "00:00:15,880",
        "to": "00:00:16,150"
      },
      "offsets": {
        "from": 15880,
        "to": 16150
      },
      "text": " show",
      "tokens": [
        {
          "text": " show",
          "timestamps": {
            "from": "00:00:15,880",
            "to": "00:00:16,150"
          },
          "offsets": {
            "from": 15880,
            "to": 16150
          },
          "id": 905,
          "p": 0.999638,
          "t_dtw": 1602
        }
      ]
    },
    {
      "timestamps": {
        "from": "00:00:16,150",
        "to": "00:00:16,520"
      },
      "offsets": {
        "from": 16150,
        "to": 16520
      },
      "text": " because",
      "tokens": [
        {
          "text": " because",
          "timestamps": {
            "from": "00:00:16,150",
            "to": "00:00:16,520"
          },
          "offsets": {
            "from": 16150,
            "to": 16520
          },
          "id": 780,
          "p": 0.866508,
          "t_dtw": 1646
        }
      ]
    },
    {
      "timestamps": {
        "from": "00:00:16,520",
        "to": "00:00:16,950"
      },
      "offsets": {
        "from": 16520,
        "to": 16950
      },
      "text": " it",
      "tokens": [
        {
          "text": " it",
          "timestamps": {
            "from": "00:00:16,520",
            "to": "00:00:16,630"
          },
          "offsets": {
            "from": 16520,
            "to": 16630
          },
          "id": 340,
          "p": 0.994905,
          "t_dtw": 1706
        }
      ]
    },
    {
      "timestamps": {
        "from": "00:00:16,950",
        "to": "00:00:17,150"
      },
      "offsets": {
        "from": 16950,
        "to": 17150
      },
      "text": " should",
      "tokens": [
        {
          "text": " should",
          "timestamps": {
            "from": "00:00:16,950",
            "to": "00:00:17,150"
          },
          "offsets": {
            "from": 16950,
            "to": 17150
          },
          "id": 815,
          "p": 0.997173,
          "t_dtw": 1728
        }
      ]
    },
    {
      "timestamps": {
        "from": "00:00:17,150",
        "to": "00:00:17,280"
      },
      "offsets": {
        "from": 17150,
        "to": 17280
      },
      "text": " be",
      "tokens": [
        {
          "text": " be",
          "timestamps": {
            "from": "00:00:17,150",
            "to": "00:00:17,280"
          },
          "offsets": {
            "from": 17150,
            "to": 17280
          },
          "id": 307,
          "p": 0.998689,
          "t_dtw": 1754
        }
      ]
    },
    {
      "timestamps": {
        "from": "00:00:17,280",
        "to": "00:00:18,000"
      },
      "offsets": {
        "from": 17280,
        "to": 18000
      },
      "text": " completely",
      "tokens": [
        {
          "text": " completely",
          "timestamps": {
            "from": "00:00:17,280",
            "to": "00:00:18,000"
          },
          "offsets": {
            "from": 17280,
            "to": 18000
          },
          "id": 3190,
          "p": 0.997581,
          "t_dtw": 1804
        }
      ]
    },
    {
      "timestamps": {
        "from": "00:00:18,000",
        "to": "00:00:19,520"
      },
      "offsets": {
        "from": 18000,
        "to": 19520
      },
      "text": " invisible",
      "tokens": [
        {
          "text": " invisible",
          "timestamps": {
            "from": "00:00:18,000",
            "to": "00:00:18,900"
          },
          "offsets": {
            "from": 18000,
            "to": 18900
          },
          "id": 14836,
          "p": 0.983128,
          "t_dtw": 1868
        }
      ]
    },
    {
      "timestamps": {
        "from": "00:00:19,520",
        "to": "00:00:19,740"
      },
      "offsets": {
        "from": 19520,
        "to": 19740
      },
      "text": ",",
      "tokens": [
        {
          "text": ",",
          "timestamps": {
            "from": "00:00:19,520",
            "to": "00:00:19,740"
          },
          "offsets": {
            "from": 19520,
            "to": 19740
          },
          "id": 11,
          "p": 0.559771,
          "t_dtw": 1882
        }
      ]
    },
    {
      "timestamps": {
        "from": "00:00:19,740",
        "to": "00:00:20,030"
      },
      "offsets": {
        "from": 19740,
        "to": 20030
      },
      "text": " but",
      "tokens": [
        {
          "text": " but",
          "timestamps": {
            "from": "00:00:19,740",
            "to": "00:00:20,030"
          },
          "offsets": {
            "from": 19740,
            "to": 20030
          },
          "id": 475,
          "p": 0.976388,
          "t_dtw": 1972
        }
      ]
    },
    {
      "timestamps": {
        "from": "00:00:20,030",
        "to": "00:00:20,280"
      },
      "offsets": {
        "from": 20030,
        "to": 20280
      },
      "text": " we",
      "tokens": [
        {
          "text": " we",
          "timestamps": {
            "from": "00:00:20,030",
            "to": "00:00:20,150"
          },
          "offsets": {
            "from": 20030,
            "to": 20150
          },
          "id": 356,
          "p": 0.994256,
          "t_dtw": 1992
        }
      ]
    },
    {
      "timestamps": {
        "from": "00:00:20,280",
        "to": "00:00:20,610"
      },
      "offsets": {
        "from": 20280,
        "to": 20610
      },
      "text": " have",
      "tokens": [
        {
          "text": " have",
          "timestamps": {
            "from": "00:00:20,280",
            "to": "00:00:20,610"
          },
          "offsets": {
            "from": 20280,
            "to": 20610
          },
          "id": 423,
          "p": 0.996717,
          "t_dtw": 2022
        }
      ]
    },
    {
      "timestamps": {
        "from": "00:00:20,610",
        "to": "00:00:21,000"
      },
      "offsets": {
        "from": 20610,
        "to": 21000
      },
      "text": " this",
      "tokens": [
        {
          "text": " this",
          "timestamps": {
            "from": "00:00:20,610",
            "to": "00:00:21,000"
          },
          "offsets": {
            "from": 20610,
            "to": 21000
          },
          "id": 428,
          "p": 0.987362,
          "t_dtw": 2044
        }
      ]
    },
    {
      "timestamps": {
        "from": "00:00:21,000",
        "to": "00:00:22,020"
      },
      "offsets": {
        "from": 21000,
        "to": 22020
      },
      "text": " repository",
      "tokens": [
        {
          "text": " repository",
          "timestamps": {
            "from": "00:00:21,000",
            "to": "00:00:21,580"
          },
          "offsets": {
            "from": 21000,
            "to": 21580
          },
          "id": 16099,
          "p": 0.994512,
          "t_dtw": 2138
        },
        {
          "text": "[_TT_1101]",
          "timestamps": {
            "from": "00:00:22,020",
            "to": "00:00:22,020"
          },
          "offsets": {
            "from": 22020,
            "to": 22020
          },
          "id": 51464,
          "p": 0.101196,
          "t_dtw": -1
        }
      ]
    },
    {
      "timestamps": {
        "from": "00:00:22,020",
        "to": "00:00:22,620"
      },
      "offsets": {
        "from": 22020,
        "to": 22620
      },
      "text": " which",
      "tokens": [
        {
          "text": " which",
          "timestamps": {
            "from": "00:00:22,070",
            "to": "00:00:22,510"
          },
          "offsets": {
            "from": 22070,
            "to": 22510
          },
          "id": 543,
          "p": 0.917655,
          "t_dtw": 2238
        }
      ]
    },
    {
      "timestamps": {
        "from": "00:00:22,620",
        "to": "00:00:23,460"
      },
      "offsets": {
        "from": 22620,
        "to": 23460
      },
      "text": " features",
      "tokens": [
        {
          "text": " features",
          "timestamps": {
            "from": "00:00:22,620",
            "to": "00:00:23,370"
          },
          "offsets": {
            "from": 22620,
            "to": 23370
          },
          "id": 3033,
          "p": 0.999268,
          "t_dtw": 2306
        }
      ]
    },
    {
      "timestamps": {
        "from": "00:00:23,460",
        "to": "00:00:23,510"
      },
      "offsets": {
        "from": 23460,
        "to": 23510
      },
      "text": " a",
      "tokens": [
        {
          "text": " a",
          "timestamps": {
            "from": "00:00:23,460",
            "to": "00:00:23,510"
          },
          "offsets": {
            "from": 23460,
            "to": 23510
          },
          "id": 257,
          "p": 0.999336,
          "t_dtw": 2338
        }
      ]
    },
    {
      "timestamps": {
        "from": "00:00:23,510",
        "to": "00:00:24,830"
      },
      "offsets": {
        "from": 23510,
        "to": 24830
      },
      "text": " comparison",
      "tokens": [
        {
          "text": " comparison",
          "timestamps": {
            "from": "00:00:23,510",
            "to": "00:00:24,230"
          },
          "offsets": {
            "from": 23510,
            "to": 24230
          },
          "id": 7208,
          "p": 0.998334,
          "t_dtw": 2404
        }
      ]
    },
    {
      "timestamps": {
        "from": "00:00:24,830",
        "to": "00:00:24,900"
      },
      "offsets": {
        "from": 24830,
        "to": 24900
      },
      "text": " and",
      "tokens": [
        {
          "text": " and",
          "timestamps": {
            "from": "00:00:24,830",
            "to": "00:00:24,900"
          },
          "offsets": {
            "from": 24830,
            "to": 24900
          },
          "id": 290,
          "p": 0.475045,
          "t_dtw": 2524
        }
      ]
    },
    {
      "timestamps": {
        "from": "00:00:24,900",
        "to": "00:00:25,110"
      },
      "offsets": {
        "from": 24900,
        "to": 25110
      },
      "text": " we",
      "tokens": [
        {
          "text": " we",
          "timestamps": {
            "from": "00:00:24,900",
            "to": "00:00:25,110"
          },
          "offsets": {
            "from": 24900,
            "to": 25110
          },
          "id": 356,
          "p": 0.964049,
          "t_dtw": 2614
        }
      ]
    },
    {
      "timestamps": {
        "from": "00:00:25,110",
        "to": "00:00:25,640"
      },
      "offsets": {
        "from": 25110,
        "to": 25640
      },
      "text": " claim",
      "tokens": [
        {
          "text": " claim",
          "timestamps": {
            "from": "00:00:25,110",
            "to": "00:00:25,640"
          },
          "offsets": {
            "from": 25110,
            "to": 25640
          },
          "id": 1624,
          "p": 0.926339,
          "t_dtw": 2644
        }
      ]
    },
    {
      "timestamps": {
        "from": "00:00:25,640",
        "to": "00:00:26,070"
      },
      "offsets": {
        "from": 25640,
        "to": 26070
      },
      "text": " that",
      "tokens": [
        {
          "text": " that",
          "timestamps": {
            "from": "00:00:25,640",
            "to": "00:00:26,070"
          },
          "offsets": {
            "from": 25640,
            "to": 26070
          },
          "id": 326,
          "p": 0.989976,
          "t_dtw": 2666
        }
      ]
    },
    {
      "timestamps": {
        "from": "00:00:26,070",
        "to": "00:00:26,280"
      },
      "offsets": {
        "from": 26070,
        "to": 26280
      },
      "text": " it",
      "tokens": [
        {
          "text": " it",
          "timestamps": {
            "from": "00:00:26,070",
            "to": "00:00:26,280"
          },
          "offsets": {
            "from": 26070,
            "to": 26280
          },
          "id": 340,
          "p": 0.988195,
          "t_dtw": 2676
        }
      ]
    },
    {
      "timestamps": {
        "from": "00:00:26,280",
        "to": "00:00:26,490"
      },
      "offsets": {
        "from": 26280,
        "to": 26490
      },
      "text": "'s",
      "tokens": [
        {
          "text": "'s",
          "timestamps": {
            "from": "00:00:26,280",
            "to": "00:00:26,490"
          },
          "offsets": {
            "from": 26280,
            "to": 26490
          },
          "id": 338,
          "p": 0.933035,
          "t_dtw": 2690
        }
      ]
    },
    {
      "timestamps": {
        "from": "00:00:26,490",
        "to": "00:00:27,020"
      },
      "offsets": {
        "from": 26490,
        "to": 27020
      },
      "text": " twice",
      "tokens": [
        {
          "text": " twice",
          "timestamps": {
            "from": "00:00:26,490",
            "to": "00:00:27,020"
          },
          "offsets": {
            "from": 26490,
            "to": 27020
          },
          "id": 5403,
          "p": 0.997472,
          "t_dtw": 2716
        }
      ]
    },
    {
      "timestamps": {
        "from": "00:00:27,020",
        "to": "00:00:27,230"
      },
      "offsets": {
        "from": 27020,
        "to": 27230
      },
      "text": " as",
      "tokens": [
        {
          "text": " as",
          "timestamps": {
            "from": "00:00:27,020",
            "to": "00:00:27,220"
          },
          "offsets": {
            "from": 27020,
            "to": 27220
          },
          "id": 355,
          "p": 0.996143,
          "t_dtw": 2732
        }
      ]
    },
    {
      "timestamps": {
        "from": "00:00:27,230",
        "to": "00:00:27,840"
      },
      "offsets": {
        "from": 27230,
        "to": 27840
      },
      "text": " fast",
      "tokens": [
        {
          "text": " fast",
          "timestamps": {
            "from": "00:00:27,230",
            "to": "00:00:27,630"
          },
          "offsets": {
            "from": 27230,
            "to": 27630
          },
          "id": 3049,
          "p": 0.997702,
          "t_dtw": 2770
        }
      ]
    },
    {
      "timestamps": {
        "from": "00:00:27,840",
        "to": "00:00:27,960"
      },
      "offsets": {
        "from": 27840,
        "to": 27960
      },
      "text": ",",
      "tokens": [
        {
          "text": ",",
          "timestamps": {
            "from": "00:00:27,840",
            "to": "00:00:27,960"
          },
          "offsets": {
            "from": 27840,
            "to": 27960
          },
          "id": 11,
          "p": 0.459317,
          "t_dtw": 2770
        }
      ]
    },
    {
      "timestamps": {
        "from": "00:00:27,960",
        "to": "00:00:28,270"
      },
      "offsets": {
        "from": 27960,
        "to": 28270
      },
      "text": " but",
      "tokens": [
        {
          "text": " but",
          "timestamps": {
            "from": "00:00:27,960",
            "to": "00:00:28,270"
          },
          "offsets": {
            "from": 27960,
            "to": 28270
          },
          "id": 475,
          "p": 0.985391,
          "t_dtw": 2800
        }
      ]
    },
    {
      "timestamps": {
        "from": "00:00:28,270",
        "to": "00:00:28,480"
      },
      "offsets": {
        "from": 28270,
        "to": 28480
      },
      "text": " in",
      "tokens": [
        {
          "text": " in",
          "timestamps": {
            "from": "00:00:28,270",
            "to": "00:00:28,480"
          },
          "offsets": {
            "from": 28270,
            "to": 28480
          },
          "id": 287,
          "p": 0.981272,
          "t_dtw": 2842
        }
      ]
    },
    {
      "timestamps": {
        "from": "00:00:28,480",
        "to": "00:00:28,900"
      },
      "offsets": {
        "from": 28480,
        "to": 28900
      },
      "text": " this",
      "tokens": [
        {
          "text": " this",
          "timestamps": {
            "from": "00:00:28,480",
            "to": "00:00:28,900"
          },
          "offsets": {
            "from": 28480,
            "to": 28900
          },
          "id": 428,
          "p": 0.998003,
          "t_dtw": 2864
        }
      ]
    },
    {
      "timestamps": {
        "from": "00:00:28,900",
        "to": "00:00:29,880"
      },
      "offsets": {
        "from": 28900,
        "to": 29880
      },
      "text": " benchmark",
      "tokens": [
        {
          "text": " benchmark",
          "timestamps": {
            "from": "00:00:28,900",
            "to": "00:00:29,320"
          },
          "offsets": {
            "from": 28900,
            "to": 29320
          },
          "id": 18335,
          "p": 0.991526,
          "t_dtw": 2938
        }
      ]
    },
    {
      "timestamps": {
        "from": "00:00:29,880",
        "to": "00:00:29,920"
      },
      "offsets": {
        "from": 29880,
        "to": 29920
      },
      "text": ",",
      "tokens": [
        {
          "text": ",",
          "timestamps": {
            "from": "00:00:29,880",
            "to": "00:00:29,920"
          },
          "offsets": {
            "from": 29880,
            "to": 29920
          },
          "id": 11,
          "p": 0.638055,
          "t_dtw": 2954
        },
        {
          "text": "[_TT_1496]",
          "timestamps": {
            "from": "00:00:29,920",
            "to": "00:00:29,920"
          },
          "offsets": {
            "from": 29920,
            "to": 29920
          },
          "id": 51859,
          "p": 0.705105,
          "t_dtw": -1
        }
      ]
    },
    {
      "timestamps": {
        "from": "00:00:29,920",
        "to": "00:00:29,920"
      },
      "offsets": {
        "from": 29920,
        "to": 29920
      },
      "text": "",
      "tokens": [
        {
          "text": "[_BEG_]",
          "timestamps": {
            "from": "00:00:29,920",
            "to": "00:00:29,920"
          },
          "offsets": {
            "from": 29920,
            "to": 29920
          },
          "id": 50363,
          "p": 0.996315,
          "t_dtw": -1
        }
      ]
    },
    {
      "timestamps": {
        "from": "00:00:29,920",
        "to": "00:00:30,210"
      },
      "offsets": {
        "from": 29920,
        "to": 30210
      },
      "text": " the",
      "tokens": [
        {
          "text": " the",
          "timestamps": {
            "from": "00:00:29,920",
            "to": "00:00:30,120"
          },
          "offsets": {
            "from": 29920,
            "to": 30120
          },
          "id": 262,
          "p": 0.313831,
          "t_dtw": 3000
        }
      ]
    },
    {
      "timestamps": {
        "from": "00:00:30,210",
        "to": "00:00:30,850"
      },
      "offsets": {
        "from": 30210,
        "to": 30850
      },
      "text": " performance",
      "tokens": [
        {
          "text": " performance",
          "timestamps": {
            "from": "00:00:30,210",
            "to": "00:00:30,850"
          },
          "offsets": {
            "from": 30210,
            "to": 30850
          },
          "id": 2854,
          "p": 0.992917,
          "t_dtw": 3052
        }
      ]
    },
    {
      "timestamps": {
        "from": "00:00:30,850",
        "to": "00:00:31,110"
      },
      "offsets": {
        "from": 30850,
        "to": 31110
      },
      "text": " gain",
      "tokens": [
        {
          "text": " gain",
          "timestamps": {
            "from": "00:00:30,850",
            "to": "00:00:31,110"
          },
          "offsets": {
            "from": 30850,
            "to": 31110
          },
          "id": 4461,
          "p": 0.994533,
          "t_dtw": 3078
        }
      ]
    },
    {
      "timestamps": {
        "from": "00:00:31,110",
        "to": "00:00:31,240"
      },
      "offsets": {
        "from": 31110,
        "to": 31240
      },
      "text": " is",
      "tokens": [
        {
          "text": " is",
          "timestamps": {
            "from": "00:00:31,110",
            "to": "00:00:31,240"
          },
          "offsets": {
            "from": 31110,
            "to": 31240
          },
          "id": 318,
          "p": 0.995197,
          "t_dtw": 3102
        }
      ]
    },
    {
      "timestamps": {
        "from": "00:00:31,240",
        "to": "00:00:31,490"
      },
      "offsets": {
        "from": 31240,
        "to": 31490
      },
      "text": " even",
      "tokens": [
        {
          "text": " even",
          "timestamps": {
            "from": "00:00:31,240",
            "to": "00:00:31,440"
          },
          "offsets": {
            "from": 31240,
            "to": 31440
          },
          "id": 772,
          "p": 0.994552,
          "t_dtw": 3126
        }
      ]
    },
    {
      "timestamps": {
        "from": "00:00:31,490",
        "to": "00:00:32,040"
      },
      "offsets": {
        "from": 31490,
        "to": 32040
      },
      "text": " better",
      "tokens": [
        {
          "text": " better",
          "timestamps": {
            "from": "00:00:31,490",
            "to": "00:00:31,790"
          },
          "offsets": {
            "from": 31490,
            "to": 31790
          },
          "id": 1365,
          "p": 0.998203,
          "t_dtw": 3168
        }
      ]
    },
    {
      "timestamps": {
        "from": "00:00:32,040",
        "to": "00:00:32,040"
      },
      "offsets": {
        "from": 32040,
        "to": 32040
      },
      "text": ".",
      "tokens": [
        {
          "text": ".",
          "timestamps": {
            "from": "00:00:32,040",
            "to": "00:00:32,040"
          },
          "offsets": {
            "from": 32040,
            "to": 32040
          },
          "id": 13,
          "p": 0.73698,
          "t_dtw": 3202
        },
        {
          "text": "[_TT_106]",
          "timestamps": {
            "from": "00:00:32,040",
            "to": "00:00:32,040"
          },
          "offsets": {
            "from": 32040,
            "to": 32040
          },
          "id": 50469,
          "p": 0.0727948,
          "t_dtw": -1
        }
      ]
    },
    {
      "timestamps": {
        "from": "00:00:32,040",
        "to": "00:00:32,040"
      },
      "offsets": {
        "from": 32040,
        "to": 32040
      },
      "text": "",
      "tokens": [
        {
          "text": "[_BEG_]",
          "timestamps": {
            "from": "00:00:32,040",
            "to": "00:00:32,040"
          },
          "offsets": {
            "from": 32040,
            "to": 32040
          },
          "id": 50363,
          "p": 0.627879,
          "t_dtw": -1
        }
      ]
    },
    {
      "timestamps": {
        "from": "00:00:32,040",
        "to": "00:00:32,810"
      },
      "offsets": {
        "from": 32040,
        "to": 32810
      },
      "text": " [",
      "tokens": [
        {
          "text": " [",
          "timestamps": {
            "from": "00:00:32,040",
            "to": "00:00:32,810"
          },
          "offsets": {
            "from": 32040,
            "to": 32810
          },
          "id": 685,
          "p": 0.139004,
          "t_dtw": 3436
        }
      ]
    },
    {
      "timestamps": {
        "from": "00:00:32,810",
        "to": "00:00:34,340"
      },
      "offsets": {
        "from": 32810,
        "to": 34340
      },
      "text": "BL",
      "tokens": [
        {
          "text": "BL",
          "timestamps": {
            "from": "00:00:32,810",
            "to": "00:00:34,340"
          },
          "offsets": {
            "from": 32810,
            "to": 34340
          },
          "id": 9148,
          "p": 0.107211,
          "t_dtw": 3436
        }
      ]
    },
    {
      "timestamps": {
        "from": "00:00:34,340",
        "to": "00:00:34,380"
      },
      "offsets": {
        "from": 34340,
        "to": 34380
      },
      "text": "ANK",
      "tokens": [
        {
          "text": "ANK",
          "timestamps": {
            "from": "00:00:34,340",
            "to": "00:00:34,380"
          },
          "offsets": {
            "from": 34340,
            "to": 34380
          },
          "id": 15154,
          "p": 0.999926,
          "t_dtw": 3436
        }
      ]
    },
    {
      "timestamps": {
        "from": "00:00:34,380",
        "to": "00:00:34,380"
      },
      "offsets": {
        "from": 34380,
        "to": 34380
      },
      "text": "_",
      "tokens": [
        {
          "text": "_",
          "timestamps": {
            "from": "00:00:34,380",
            "to": "00:00:34,380"
          },
          "offsets": {
            "from": 34380,
            "to": 34380
          },
          "id": 62,
          "p": 0.97886,
          "t_dtw": 3436
        }
      ]
    },
    {
      "timestamps": {
        "from": "00:00:34,380",
        "to": "00:00:34,380"
      },
      "offsets": {
        "from": 34380,
        "to": 34380
      },
      "text": "AUD",
      "tokens": [
        {
          "text": "AUD",
          "timestamps": {
            "from": "00:00:34,380",
            "to": "00:00:34,380"
          },
          "offsets": {
            "from": 34380,
            "to": 34380
          },
          "id": 48877,
          "p": 0.999683,
          "t_dtw": 3436
        }
      ]
    },
    {
      "timestamps": {
        "from": "00:00:34,380",
        "to": "00:00:34,380"
      },
      "offsets": {
        "from": 34380,
        "to": 34380
      },
      "text": "IO",
      "tokens": [
        {
          "text": "IO",
          "timestamps": {
            "from": "00:00:34,380",
            "to": "00:00:34,380"
          },
          "offsets": {
            "from": 34380,
            "to": 34380
          },
          "id": 9399,
          "p": 0.999964,
          "t_dtw": 3436
        }
      ]
    },
    {
      "timestamps": {
        "from": "00:00:34,380",
        "to": "00:00:42,040"
      },
      "offsets": {
        "from": 34380,
        "to": 42040
      },
      "text": "]",
      "tokens": [
        {
          "text": "]",
          "timestamps": {
            "from": "00:00:34,380",
            "to": "00:00:34,380"
          },
          "offsets": {
            "from": 34380,
            "to": 34380
          },
          "id": 60,
          "p": 0.999087,
          "t_dtw": 3436
        },
        {
          "text": "[_TT_500]",
          "timestamps": {
            "from": "00:00:42,040",
            "to": "00:00:42,040"
          },
          "offsets": {
            "from": 42040,
            "to": 42040
          },
          "id": 50863,
          "p": 0.31795,
          "t_dtw": -1
        }
      ]
    }
  ]
}