[
  {
    "text": "There",
    "startMs": 40,
    "endMs": 800,
    "timestampMs": 2620,
    "confidence": 0.729951
  },
  {
    "text": " are",
    "startMs": 800,
    "endMs": 1280,
    "timestampMs": 2840,
    "confidence": 0.994903
  },
  {
    "text": " further",
    "startMs": 1280,
    "endMs": 2520,
    "timestampMs": 3160,
    "confidence": 0.99218
  },
  {
    "text": " challenges",
    "startMs": 2520,
    "endMs": 4180,
    "timestampMs": 3720,
    "confidence": 0.995144
  },
  {
    "text": " to",
    "startMs": 4180,
    "endMs": 4220,
    "timestampMs": 4280,
    "confidence": 0.967113
  },
  {
    "text": " make",
    "startMs": 4220,
    "endMs": 4670,
    "timestampMs": 4460,
    "confidence": 0.990197
  },
  {
    "text": " it",
    "startMs": 4670,
    "endMs": 4950,
    "timestampMs": 4620,
    "confidence": 0.992971
  },
  {
    "text": " work",
    "startMs": 4950,
    "endMs": 5360,
    "timestampMs": 4980,
    "confidence": 0.991414
  },
  {
    "text": " with",
    "startMs": 5360,
    "endMs": 5830,
    "timestampMs": 5640,
    "confidence": 0.979516
  },
  {
    "text": " React",
    "startMs": 5830,
    "endMs": 6320,
    "timestampMs": 6220,
    "confidence": 0.884889
  },
  {
    "text": ".",
    "startMs": 6320,
    "endMs": 6800,
    "timestampMs": 6800,
    "confidence": 0.955152
  },
  {
    "text": " The",
    "startMs": 6800,
    "endMs": 7020,
    "timestampMs": 7020,
    "confidence": 0.990278
  },
  {
    "text": " first",
    "startMs": 7020,
    "endMs": 7280,
    "timestampMs": 7220,
    "confidence": 0.996995
  },
  {
    "text": " challenge",
    "startMs": 7280,
    "endMs": 7870,
    "timestampMs": 7580,
    "confidence": 0.971476
  },
  {
    "text": " is",
    "startMs": 7870,
    "endMs": 7940,
    "timestampMs": 7820,
    "confidence": 0.995775
  },
  {
    "text": " that",
    "startMs": 7940,
    "endMs": 8290,
    "timestampMs": 8100,
    "confidence": 0.977666
  },
  {
    "text": " we",
    "startMs": 8290,
    "endMs": 8300,
    "timestampMs": 8380,
    "confidence": 0.933059
  },
  {
    "text": " are",
    "startMs": 8300,
    "endMs": 8420,
    "timestampMs": 8480,
    "confidence": 0.913868
  },
  {
    "text": " essentially",
    "startMs": 8420,
    "endMs": 8920,
    "timestampMs": 8920,
    "confidence": 0.987044
  },
  {
    "text": " setting",
    "startMs": 8920,
    "endMs": 9550,
    "timestampMs": 9420,
    "confidence": 0.998799
  },
  {
    "text": " a",
    "startMs": 9550,
    "endMs": 9610,
    "timestampMs": 9700,
    "confidence": 0.997721
  },
  {
    "text": " state",
    "startMs": 9610,
    "endMs": 10050,
    "timestampMs": 10080,
    "confidence": 0.994063
  },
  {
    "text": " during",
    "startMs": 10050,
    "endMs": 10580,
    "timestampMs": 10480,
    "confidence": 0.999218
  },
  {
    "text": " the",
    "startMs": 10580,
    "endMs": 10870,
    "timestampMs": 10900,
    "confidence": 0.99931
  },
  {
    "text": " render",
    "startMs": 10870,
    "endMs": 11400,
    "timestampMs": 11280,
    "confidence": 0.985652
  },
  {
    "text": " cycle",
    "startMs": 11400,
    "endMs": 11920,
    "timestampMs": 11880,
    "confidence": 0.894101
  },
  {
    "text": ",",
    "startMs": 11920,
    "endMs": 12040,
    "timestampMs": 11880,
    "confidence": 0.846163
  },
  {
    "text": " which",
    "startMs": 12040,
    "endMs": 12120,
    "timestampMs": 12160,
    "confidence": 0.876515
  },
  {
    "text": " is",
    "startMs": 12120,
    "endMs": 12290,
    "timestampMs": 12280,
    "confidence": 0.999516
  },
  {
    "text": " normally",
    "startMs": 12290,
    "endMs": 12900,
    "timestampMs": 12580,
    "confidence": 0.999275
  },
  {
    "text": " prohibited",
    "startMs": 12900,
    "endMs": 13680,
    "timestampMs": 13180,
    "confidence": 0.998948
  },
  {
    "text": ".",
    "startMs": 13680,
    "endMs": 13940,
    "timestampMs": 13800,
    "confidence": 0.957488
  },
  {
    "text": " And",
    "startMs": 13940,
    "endMs": 14220,
    "timestampMs": 14300,
    "confidence": 0.999775
  },
  {
    "text": " the",
    "startMs": 14220,
    "endMs": 14520,
    "timestampMs": 14680,
    "confidence": 0.99918
  },
  {
    "text": " second",
    "startMs": 14520,
    "endMs": 15060,
    "timestampMs": 15040,
    "confidence": 0.999333
  },
  {
    "text": " challenge",
    "startMs": 15060,
    "endMs": 15910,
    "timestampMs": 15700,
    "confidence": 0.998967
  },
  {
    "text": " is",
    "startMs": 15910,
    "endMs": 16100,
    "timestampMs": 16020,
    "confidence": 0.999401
  },
  {
    "text": " that",
    "startMs": 16100,
    "endMs": 16650,
    "timestampMs": 16320,
    "confidence": 0.997992
  },
  {
    "text": " this",
    "startMs": 16650,
    "endMs": 16870,
    "timestampMs": 16880,
    "confidence": 0.987453
  },
  {
    "text": " is",
    "startMs": 16870,
    "endMs": 17050,
    "timestampMs": 17080,
    "confidence": 0.998586
  },
  {
    "text": " not",
    "startMs": 17050,
    "endMs": 17420,
    "timestampMs": 17340,
    "confidence": 0.999466
  },
  {
    "text": " a",
    "startMs": 17420,
    "endMs": 17440,
    "timestampMs": 17640,
    "confidence": 0.968356
  },
  {
    "text": " React",
    "startMs": 17440,
    "endMs": 17850,
    "timestampMs": 18060,
    "confidence": 0.963062
  },
  {
    "text": " hook",
    "startMs": 17850,
    "endMs": 18180,
    "timestampMs": 18360,
    "confidence": 0.971931
  },
  {
    "text": ",",
    "startMs": 18180,
    "endMs": 18360,
    "timestampMs": 18480,
    "confidence": 0.372087
  },
  {
    "text": " so",
    "startMs": 18360,
    "endMs": 18560,
    "timestampMs": 18640,
    "confidence": 0.998951
  },
  {
    "text": " how",
    "startMs": 18560,
    "endMs": 18870,
    "timestampMs": 18880,
    "confidence": 0.998213
  },
  {
    "text": " the",
    "startMs": 18870,
    "endMs": 19180,
    "timestampMs": 19060,
    "confidence": 0.878778
  },
  {
    "text": " hell",
    "startMs": 19180,
    "endMs": 19590,
    "timestampMs": 19140,
    "confidence": 0.998696
  },
  {
    "text": " do",
    "startMs": 19590,
    "endMs": 19790,
    "timestampMs": 19320,
    "confidence": 0.996995
  },
  {
    "text": " we",
    "startMs": 19790,
    "endMs": 19980,
    "timestampMs": 19500,
    "confidence": 0.991249
  },
  {
    "text": " update",
    "startMs": 19980,
    "endMs": 20640,
    "timestampMs": 19960,
    "confidence": 0.999112
  },
  {
    "text": " the",
    "startMs": 20640,
    "endMs": 20920,
    "timestampMs": 20640,
    "confidence": 0.999039
  },
  {
    "text": " component",
    "startMs": 20920,
    "endMs": 21970,
    "timestampMs": 21200,
    "confidence": 0.998426
  },
  {
    "text": " if",
    "startMs": 21970,
    "endMs": 22430,
    "timestampMs": 22180,
    "confidence": 0.647839
  },
  {
    "text": " this",
    "startMs": 22430,
    "endMs": 22680,
    "timestampMs": 22700,
    "confidence": 0.999241
  },
  {
    "text": " is",
    "startMs": 22680,
    "endMs": 22880,
    "timestampMs": 22900,
    "confidence": 0.953788
  },
  {
    "text": " not",
    "startMs": 22880,
    "endMs": 23200,
    "timestampMs": 23180,
    "confidence": 0.996888
  },
  {
    "text": " a",
    "startMs": 23200,
    "endMs": 23260,
    "timestampMs": 23480,
    "confidence": 0.965808
  },
  {
    "text": " hook",
    "startMs": 23260,
    "endMs": 23540,
    "timestampMs": 23760,
    "confidence": 0.996839
  },
  {
    "text": " which",
    "startMs": 23540,
    "endMs": 23880,
    "timestampMs": 24080,
    "confidence": 0.907788
  },
  {
    "text": " is",
    "startMs": 23880,
    "endMs": 23940,
    "timestampMs": 24440,
    "confidence": 0.999649
  },
  {
    "text": " reactive",
    "startMs": 23940,
    "endMs": 24440,
    "timestampMs": 24620,
    "confidence": 0.98775
  },
  {
    "text": "?",
    "startMs": 24440,
    "endMs": 24640,
    "timestampMs": 24620,
    "confidence": 0.826494
  },
  {
    "text": " [",
    "startMs": 24640,
    "endMs": 25850,
    "timestampMs": 25720,
    "confidence": 0.0603518
  },
  {
    "text": "BL",
    "startMs": 25850,
    "endMs": 26700,
    "timestampMs": 26680,
    "confidence": 0.770258
  },
  {
    "text": "ANK",
    "startMs": 26700,
    "endMs": 26700,
    "timestampMs": 26680,
    "confidence": 0.999712
  },
  {
    "text": "_",
    "startMs": 26700,
    "endMs": 26700,
    "timestampMs": 26680,
    "confidence": 0.985167
  },
  {
    "text": "AUD",
    "startMs": 26700,
    "endMs": 26700,
    "timestampMs": 26680,
    "confidence": 0.999415
  },
  {
    "text": "IO",
    "startMs": 26700,
    "endMs": 26700,
    "timestampMs": 26680,
    "confidence": 0.999968
  },
  {
    "text": "]",
    "startMs": 26700,
    "endMs": 34640,
    "timestampMs": 26680,
    "confidence": 0.99926
  }
]
