[
  {
    "text": "In",
    "startMs": 40,
    "endMs": 1400,
    "timestampMs": 3420,
    "confidence": 0.860183
  },
  {
    "text": " summary",
    "startMs": 1400,
    "endMs": 3500,
    "timestampMs": 3960,
    "confidence": 0.997716
  },
  {
    "text": ",",
    "startMs": 3500,
    "endMs": 4360,
    "timestampMs": 5020,
    "confidence": 0.86125
  },
  {
    "text": " Rem",
    "startMs": 4360,
    "endMs": 4740,
    "timestampMs": 5020,
    "confidence": 0.652985
  },
  {
    "text": "otion",
    "startMs": 4740,
    "endMs": 4990,
    "timestampMs": 5220,
    "confidence": 0.958139
  },
  {
    "text": " Media",
    "startMs": 4990,
    "endMs": 5460,
    "timestampMs": 5520,
    "confidence": 0.949759
  },
  {
    "text": " Par",
    "startMs": 5460,
    "endMs": 5740,
    "timestampMs": 5780,
    "confidence": 0.0684576
  },
  {
    "text": "ter",
    "startMs": 5740,
    "endMs": 6020,
    "timestampMs": 5940,
    "confidence": 0.31758
  },
  {
    "text": " is",
    "startMs": 6020,
    "endMs": 6200,
    "timestampMs": 6240,
    "confidence": 0.988127
  },
  {
    "text": " a",
    "startMs": 6200,
    "endMs": 6400,
    "timestampMs": 6700,
    "confidence": 0.990673
  },
  {
    "text": " modern",
    "startMs": 6400,
    "endMs": 7210,
    "timestampMs": 7120,
    "confidence": 0.980497
  },
  {
    "text": " new",
    "startMs": 7210,
    "endMs": 7410,
    "timestampMs": 7600,
    "confidence": 0.695338
  },
  {
    "text": " multimedia",
    "startMs": 7410,
    "endMs": 8140,
    "timestampMs": 8120,
    "confidence": 0.972996
  },
  {
    "text": " library",
    "startMs": 8140,
    "endMs": 8560,
    "timestampMs": 8580,
    "confidence": 0.980239
  },
  {
    "text": " for",
    "startMs": 8560,
    "endMs": 8780,
    "timestampMs": 8880,
    "confidence": 0.972689
  },
  {
    "text": " JavaScript",
    "startMs": 8780,
    "endMs": 9840,
    "timestampMs": 9400,
    "confidence": 0.965742
  },
  {
    "text": ".",
    "startMs": 9840,
    "endMs": 10470,
    "timestampMs": 10500,
    "confidence": 0.928228
  },
  {
    "text": " It",
    "startMs": 10470,
    "endMs": 10510,
    "timestampMs": 10600,
    "confidence": 0.979641
  },
  {
    "text": " runs",
    "startMs": 10510,
    "endMs": 10990,
    "timestampMs": 10980,
    "confidence": 0.999138
  },
  {
    "text": " on",
    "startMs": 10990,
    "endMs": 11200,
    "timestampMs": 11340,
    "confidence": 0.99747
  },
  {
    "text": " the",
    "startMs": 11200,
    "endMs": 11540,
    "timestampMs": 11520,
    "confidence": 0.994317
  },
  {
    "text": " web",
    "startMs": 11540,
    "endMs": 11870,
    "timestampMs": 11760,
    "confidence": 0.915761
  },
  {
    "text": ",",
    "startMs": 11870,
    "endMs": 12280,
    "timestampMs": 12340,
    "confidence": 0.781912
  },
  {
    "text": " in",
    "startMs": 12280,
    "endMs": 12340,
    "timestampMs": 12460,
    "confidence": 0.989917
  },
  {
    "text": " Node",
    "startMs": 12340,
    "endMs": 12800,
    "timestampMs": 12660,
    "confidence": 0.822407
  },
  {
    "text": ".",
    "startMs": 12800,
    "endMs": 13010,
    "timestampMs": 12660,
    "confidence": 0.962616
  },
  {
    "text": "js",
    "startMs": 13010,
    "endMs": 13710,
    "timestampMs": 12940,
    "confidence": 0.980907
  },
  {
    "text": " and",
    "startMs": 13710,
    "endMs": 13710,
    "timestampMs": 13940,
    "confidence": 0.535387
  },
  {
    "text": " B",
    "startMs": 13710,
    "endMs": 13820,
    "timestampMs": 14240,
    "confidence": 0.419429
  },
  {
    "text": "UN",
    "startMs": 13820,
    "endMs": 14050,
    "timestampMs": 14240,
    "confidence": 0.647439
  },
  {
    "text": ".",
    "startMs": 14050,
    "endMs": 14470,
    "timestampMs": 15300,
    "confidence": 0.963979
  },
  {
    "text": " It",
    "startMs": 14470,
    "endMs": 15600,
    "timestampMs": 15740,
    "confidence": 0.913297
  },
  {
    "text": " embraces",
    "startMs": 15600,
    "endMs": 16100,
    "timestampMs": 16340,
    "confidence": 0.997976
  },
  {
    "text": " web",
    "startMs": 16100,
    "endMs": 16600,
    "timestampMs": 16660,
    "confidence": 0.933132
  },
  {
    "text": " standards",
    "startMs": 16600,
    "endMs": 17200,
    "timestampMs": 17180,
    "confidence": 0.950655
  },
  {
    "text": " and",
    "startMs": 17200,
    "endMs": 17500,
    "timestampMs": 17640,
    "confidence": 0.835855
  },
  {
    "text": " the",
    "startMs": 17500,
    "endMs": 17880,
    "timestampMs": 17800,
    "confidence": 0.996136
  },
  {
    "text": " async",
    "startMs": 17880,
    "endMs": 18220,
    "timestampMs": 18340,
    "confidence": 0.987926
  },
  {
    "text": " nature",
    "startMs": 18220,
    "endMs": 18760,
    "timestampMs": 19020,
    "confidence": 0.998262
  },
  {
    "text": " of",
    "startMs": 18760,
    "endMs": 18940,
    "timestampMs": 19340,
    "confidence": 0.999786
  },
  {
    "text": " JavaScript",
    "startMs": 18940,
    "endMs": 19830,
    "timestampMs": 19940,
    "confidence": 0.978541
  },
  {
    "text": ",",
    "startMs": 19830,
    "endMs": 20020,
    "timestampMs": 20520,
    "confidence": 0.93473
  },
  {
    "text": " requires",
    "startMs": 20020,
    "endMs": 20820,
    "timestampMs": 21080,
    "confidence": 0.997748
  },
  {
    "text": " minimal",
    "startMs": 20820,
    "endMs": 21370,
    "timestampMs": 21560,
    "confidence": 0.992509
  },
  {
    "text": " data",
    "startMs": 21370,
    "endMs": 21730,
    "timestampMs": 21980,
    "confidence": 0.990248
  },
  {
    "text": " to",
    "startMs": 21730,
    "endMs": 21940,
    "timestampMs": 22160,
    "confidence": 0.996348
  },
  {
    "text": " be",
    "startMs": 21940,
    "endMs": 22090,
    "timestampMs": 22340,
    "confidence": 0.999584
  },
  {
    "text": " fet",
    "startMs": 22090,
    "endMs": 22360,
    "timestampMs": 22560,
    "confidence": 0.99597
  },
  {
    "text": "ched",
    "startMs": 22360,
    "endMs": 22730,
    "timestampMs": 22800,
    "confidence": 0.999361
  },
  {
    "text": " and",
    "startMs": 22730,
    "endMs": 23360,
    "timestampMs": 23520,
    "confidence": 0.781564
  },
  {
    "text": " does",
    "startMs": 23360,
    "endMs": 23470,
    "timestampMs": 23760,
    "confidence": 0.938448
  },
  {
    "text": " not",
    "startMs": 23470,
    "endMs": 23940,
    "timestampMs": 23920,
    "confidence": 0.990966
  },
  {
    "text": " block",
    "startMs": 23940,
    "endMs": 24560,
    "timestampMs": 24420,
    "confidence": 0.999093
  },
  {
    "text": " the",
    "startMs": 24560,
    "endMs": 24720,
    "timestampMs": 24700,
    "confidence": 0.998506
  },
  {
    "text": " UI",
    "startMs": 24720,
    "endMs": 24900,
    "timestampMs": 25060,
    "confidence": 0.982735
  },
  {
    "text": " thread",
    "startMs": 24900,
    "endMs": 25490,
    "timestampMs": 25520,
    "confidence": 0.968161
  },
  {
    "text": ".",
    "startMs": 25490,
    "endMs": 25750,
    "timestampMs": 26820,
    "confidence": 0.992854
  },
  {
    "text": " It",
    "startMs": 25750,
    "endMs": 26000,
    "timestampMs": 27140,
    "confidence": 0.99243
  },
  {
    "text": " supports",
    "startMs": 26000,
    "endMs": 27040,
    "timestampMs": 27560,
    "confidence": 0.996101
  },
  {
    "text": " the",
    "startMs": 27040,
    "endMs": 27060,
    "timestampMs": 27900,
    "confidence": 0.993623
  },
  {
    "text": " nine",
    "startMs": 27060,
    "endMs": 27450,
    "timestampMs": 28240,
    "confidence": 0.886813
  },
  {
    "text": " most",
    "startMs": 27450,
    "endMs": 27840,
    "timestampMs": 28600,
    "confidence": 0.998727
  },
  {
    "text": " common",
    "startMs": 27840,
    "endMs": 28430,
    "timestampMs": 29000,
    "confidence": 0.998064
  },
  {
    "text": " container",
    "startMs": 28430,
    "endMs": 29340,
    "timestampMs": 29580,
    "confidence": 0.99507
  },
  {
    "text": " formats",
    "startMs": 29340,
    "endMs": 30010,
    "timestampMs": 30080,
    "confidence": 0.999519
  },
  {
    "text": " and",
    "startMs": 30010,
    "endMs": 30400,
    "timestampMs": 30940,
    "confidence": 0.964343
  },
  {
    "text": " un",
    "startMs": 30400,
    "endMs": 30780,
    "timestampMs": 31240,
    "confidence": 0.998915
  },
  {
    "text": "ifies",
    "startMs": 30780,
    "endMs": 31290,
    "timestampMs": 31440,
    "confidence": 0.999237
  },
  {
    "text": " them",
    "startMs": 31290,
    "endMs": 31780,
    "timestampMs": 31800,
    "confidence": 0.999565
  },
  {
    "text": " under",
    "startMs": 31780,
    "endMs": 32410,
    "timestampMs": 32400,
    "confidence": 0.993218
  },
  {
    "text": " one",
    "startMs": 32410,
    "endMs": 32870,
    "timestampMs": 32740,
    "confidence": 0.998803
  },
  {
    "text": " simple",
    "startMs": 32870,
    "endMs": 33550,
    "timestampMs": 33320,
    "confidence": 0.989791
  },
  {
    "text": " to",
    "startMs": 33550,
    "endMs": 33960,
    "timestampMs": 33540,
    "confidence": 0.682487
  },
  {
    "text": " use",
    "startMs": 33960,
    "endMs": 34170,
    "timestampMs": 33820,
    "confidence": 0.911602
  },
  {
    "text": " API",
    "startMs": 34170,
    "endMs": 34540,
    "timestampMs": 34500,
    "confidence": 0.994981
  },
  {
    "text": ".",
    "startMs": 34540,
    "endMs": 35740,
    "timestampMs": 35940,
    "confidence": 0.950704
  },
  {
    "text": " Media",
    "startMs": 35740,
    "endMs": 35750,
    "timestampMs": 36120,
    "confidence": 0.963754
  },
  {
    "text": " Par",
    "startMs": 35750,
    "endMs": 36210,
    "timestampMs": 36320,
    "confidence": 0.497891
  },
  {
    "text": "ter",
    "startMs": 36210,
    "endMs": 36940,
    "timestampMs": 36320,
    "confidence": 0.945256
  },
  {
    "text": " has",
    "startMs": 36940,
    "endMs": 37140,
    "timestampMs": 37060,
    "confidence": 0.987828
  },
  {
    "text": " no",
    "startMs": 37140,
    "endMs": 37430,
    "timestampMs": 37420,
    "confidence": 0.99851
  },
  {
    "text": " dependencies",
    "startMs": 37430,
    "endMs": 39720,
    "timestampMs": 38080,
    "confidence": 0.993542
  },
  {
    "text": ".",
    "startMs": 39720,
    "endMs": 39760,
    "timestampMs": 39240,
    "confidence": 0.939245
  },
  {
    "text": " By",
    "startMs": 39760,
    "endMs": 39760,
    "timestampMs": 39840,
    "confidence": 0.850285
  },
  {
    "text": " taking",
    "startMs": 39760,
    "endMs": 40320,
    "timestampMs": 40220,
    "confidence": 0.99979
  },
  {
    "text": " care",
    "startMs": 40320,
    "endMs": 40620,
    "timestampMs": 40620,
    "confidence": 0.999821
  },
  {
    "text": " of",
    "startMs": 40620,
    "endMs": 40850,
    "timestampMs": 40980,
    "confidence": 0.999752
  },
  {
    "text": " all",
    "startMs": 40850,
    "endMs": 41160,
    "timestampMs": 41380,
    "confidence": 0.999443
  },
  {
    "text": " the",
    "startMs": 41160,
    "endMs": 41310,
    "timestampMs": 41520,
    "confidence": 0.999554
  },
  {
    "text": " necessary",
    "startMs": 41310,
    "endMs": 42090,
    "timestampMs": 42060,
    "confidence": 0.999542
  },
  {
    "text": " pre",
    "startMs": 42090,
    "endMs": 42350,
    "timestampMs": 42480,
    "confidence": 0.99795
  },
  {
    "text": "-",
    "startMs": 42350,
    "endMs": 42430,
    "timestampMs": 42560,
    "confidence": 0.856761
  },
  {
    "text": "processing",
    "startMs": 42430,
    "endMs": 43310,
    "timestampMs": 43100,
    "confidence": 0.971304
  },
  {
    "text": ",",
    "startMs": 43310,
    "endMs": 43960,
    "timestampMs": 44120,
    "confidence": 0.733506
  },
  {
    "text": " Media",
    "startMs": 43960,
    "endMs": 44030,
    "timestampMs": 44380,
    "confidence": 0.821851
  },
  {
    "text": " Par",
    "startMs": 44030,
    "endMs": 44330,
    "timestampMs": 44560,
    "confidence": 0.953157
  },
  {
    "text": "ter",
    "startMs": 44330,
    "endMs": 44630,
    "timestampMs": 44780,
    "confidence": 0.982727
  },
  {
    "text": " makes",
    "startMs": 44630,
    "endMs": 45220,
    "timestampMs": 45240,
    "confidence": 0.993724
  },
  {
    "text": " it",
    "startMs": 45220,
    "endMs": 45400,
    "timestampMs": 45460,
    "confidence": 0.973825
  },
  {
    "text": " so",
    "startMs": 45400,
    "endMs": 45640,
    "timestampMs": 45700,
    "confidence": 0.714818
  },
  {
    "text": " much",
    "startMs": 45640,
    "endMs": 46170,
    "timestampMs": 45960,
    "confidence": 0.936115
  },
  {
    "text": " easier",
    "startMs": 46170,
    "endMs": 47000,
    "timestampMs": 46460,
    "confidence": 0.999863
  },
  {
    "text": " to",
    "startMs": 47000,
    "endMs": 47240,
    "timestampMs": 47120,
    "confidence": 0.996953
  },
  {
    "text": " harness",
    "startMs": 47240,
    "endMs": 48180,
    "timestampMs": 47500,
    "confidence": 0.998826
  },
  {
    "text": " the",
    "startMs": 48180,
    "endMs": 48570,
    "timestampMs": 47920,
    "confidence": 0.999668
  },
  {
    "text": " power",
    "startMs": 48570,
    "endMs": 49270,
    "timestampMs": 48260,
    "confidence": 0.998791
  },
  {
    "text": " of",
    "startMs": 49270,
    "endMs": 49510,
    "timestampMs": 48640,
    "confidence": 0.999577
  },
  {
    "text": " Web",
    "startMs": 49510,
    "endMs": 49900,
    "timestampMs": 48880,
    "confidence": 0.936215
  },
  {
    "text": "Cod",
    "startMs": 49900,
    "endMs": 50440,
    "timestampMs": 49120,
    "confidence": 0.707915
  },
  {
    "text": "ec",
    "startMs": 50440,
    "endMs": 50710,
    "timestampMs": 49180,
    "confidence": 0.787116
  },
  {
    "text": "s",
    "startMs": 50710,
    "endMs": 50710,
    "timestampMs": 50400,
    "confidence": 0.680265
  },
  {
    "text": ".",
    "startMs": 50710,
    "endMs": 51160,
    "timestampMs": 50400,
    "confidence": 0.960054
  }
]
